tempmorph/__init__.py
tempmorph/conv.py
tempmorph-0.0.1.dist-info/LICENCE
tempmorph-0.0.1.dist-info/METADATA
tempmorph-0.0.1.dist-info/WHEEL
tempmorph-0.0.1.dist-info/top_level.txt
tempmorph-0.0.1.dist-info/RECORD
