Metadata-Version: 2.1
Name: tempmorph
Version: 0.0.1
Summary: A package that helps you with converting temperature scales. Currently works with Celcius, Fahrenheit, Kelvin, Reaumur, and Rankine.
Home-page: https://github.com/pypa/sampleproject
Author: Sharkfin07
Author-email: mzidanek@gmail.com
Project-URL: Bug Tracker, https://github.com/pypa/sampleproject/issues
Classifier: Programming Language :: Python :: 3
Classifier: License :: OSI Approved :: MIT License
Classifier: Operating System :: OS Independent
Requires-Python: >=3.6
License-File: LICENCE
